youqu3/__init__.py
youqu3/__version__.py
youqu3/assert.py
youqu3/cmd.py
youqu3/dogtail.py
youqu3/exception.py
youqu3/file.py
youqu3/image.py
youqu3/mousekey.py
youqu3/ocr.py
youqu3/requests.py
youqu3/sleepx.py
youqu3/webui.py
youqu3/_setting/__init__.py
youqu3/_setting/_dynamic.py
youqu3/_setting/_setting.py
youqu3/driver/__init__.py
youqu3/driver/cli.py
youqu3/driver/init.py
youqu3/driver/remote.py
youqu3/driver/run.py
youqu3/tpl/${app_name}_assert.py-tpl
youqu3/tpl/.env-tpl
youqu3/tpl/.gitignore-tpl
youqu3/tpl/__init__.py-tpl
youqu3/tpl/config.py-tpl
youqu3/tpl/conftest.py-tpl
youqu3/tpl/debug.py-tpl.py
youqu3/tpl/mycase.csv-tpl
youqu3/tpl/requirements.txt-tpl
youqu3/tpl/case/__init__.py-tpl
youqu3/tpl/case/base_case.py-tpl
youqu3/tpl/case/test_mycase_001.py-tpl
youqu3/tpl/case/test_mycase_002.py-tpl
youqu3/tpl/case/assert_res/readme
youqu3/tpl/method/${app_name}_method.py-tpl
youqu3/tpl/method/base_method.py-tpl
youqu3/tpl/method/other.ini-tpl
youqu3/tpl/method/other_method.py-tpl
youqu3/tpl/method/ui.ini-tpl
youqu3/tpl/method/image_res/readme
youqu3/tpl/method/static_res/readme
youqu3/vendor/__init__.py
youqu3-2024.6.14.dist-info/METADATA
youqu3-2024.6.14.dist-info/WHEEL
youqu3-2024.6.14.dist-info/entry_points.txt
youqu3-2024.6.14.dist-info/licenses/LICENSE
youqu3-2024.6.14.dist-info/RECORD
