Metadata-Version: 2.1
Name: youqu3
Version: 2024.6.14
Summary: YouQu-Next
Author-email: mikigo <huangmingqiang@uniontech.com>
License: GPL2.0
License-File: LICENSE
Requires-Python: >=3.7
Requires-Dist: allure-custom
Requires-Dist: allure-pytest
Requires-Dist: click
Requires-Dist: easyprocess
Requires-Dist: funnylog
Requires-Dist: pytest
Requires-Dist: pytest-json-report
Requires-Dist: pytest-mark-manage
Requires-Dist: pytest-rerunfailures
Requires-Dist: pytest-timeout
Requires-Dist: rich
Provides-Extra: dbus
Requires-Dist: youqu-dbus; extra == 'dbus'
Provides-Extra: desktop-ui
Requires-Dist: pdocr-rpc; extra == 'desktop-ui'
Requires-Dist: youqu-dogtail; extra == 'desktop-ui'
Requires-Dist: youqu-imagecenter-rpc; extra == 'desktop-ui'
Requires-Dist: youqu-mousekey; extra == 'desktop-ui'
Provides-Extra: http
Requires-Dist: requests; extra == 'http'
Provides-Extra: webui
Requires-Dist: pytest-youqu-playwright; extra == 'webui'
